qreader.py
documentation/benchmark/resizes.py
documentation/benchmark/rotations.py
venv/bin/activate_this.py
venv/bin/read_zbar.py
qreader-3.14.dist-info/LICENSE
qreader-3.14.dist-info/METADATA
qreader-3.14.dist-info/WHEEL
qreader-3.14.dist-info/top_level.txt
qreader-3.14.dist-info/RECORD
