Metadata-Version: 2.1
Name: qreader
Version: 3.14
Summary: Robust and Straight-Forward solution for reading difficult and tricky QR codes within images in Python. Supported by a YOLOv8 QR Segmentation model.
Home-page: https://github.com/Eric-Canas/qreader
Author: Eric Canas
Author-email: elcorreodeharu@gmail.com
License: MIT
Classifier: Development Status :: 5 - Production/Stable
Classifier: Intended Audience :: Developers
Classifier: Intended Audience :: Science/Research
Classifier: License :: OSI Approved :: MIT License
Classifier: Operating System :: OS Independent
Classifier: Programming Language :: Python :: 3
Classifier: Topic :: Scientific/Engineering :: Image Recognition
Classifier: Topic :: Software Development :: Libraries :: Python Modules
Classifier: Topic :: Utilities
License-File: LICENSE
Requires-Dist: numpy
Requires-Dist: opencv-python
Requires-Dist: pyzbar
Requires-Dist: qrdet >=2.5
